Sylveon/__init__.py
Sylveon/array_generator.py
Sylveon/graph.py
Sylveon/graph_generator.py
Sylveon/io_file.py
Sylveon/string_generator.py
Sylveon/utils/__init__.py
Sylveon/utils/constant.py
Sylveon/utils/global_config.py
Sylveon/utils/rand.py
Sylveon-0.0.0.dist-info/LICENSE
Sylveon-0.0.0.dist-info/METADATA
Sylveon-0.0.0.dist-info/WHEEL
Sylveon-0.0.0.dist-info/top_level.txt
Sylveon-0.0.0.dist-info/RECORD
