Metadata-Version: 2.1
Name: Sylveon
Version: 0.0.0
Summary: A random number generator on algorithmic questions.
Home-page: https://github.com/Ujimatsu-Chiya/Sylveon
Author: Ujimatsu Chiya
Author-email: ujimatsuchiya016@gmail.com
Maintainer: Ujimatsu Chiya
Maintainer-email: ujimatsuchiya016@gmail.com
License: LGPL-3.0
Keywords: python algorithm icpc acm oi
Classifier: Development Status :: 1 - Planning
Classifier: Intended Audience :: Developers
Classifier: Intended Audience :: Education
Classifier: License :: OSI Approved :: GNU Lesser General Public License v3 (LGPLv3)
Classifier: Programming Language :: Python :: 3
Classifier: Programming Language :: Python :: 3.10
License-File: LICENSE
